

[
  {
    "name": "Samiul",
    "age": 25,
    "city": "Dhaka"

  },
  {
    "name": "Rafi",
    "age": 23,
    "city": "Dhaka"

  },
  {
    "name": "Jahin",
    "age": 22,
    "city": "Dhaka"

  },
  {
    "name": "Mim",
    "age": 20,
    "city": "Dhaka"

  },
  {
    "name": "Samiul",
    "age": 25,
    "city": "Dhaka"

  },
  {
    "name": "Rafi",
    "age": 23,
    "city": "Dhaka"

  },
  {
    "name": "Jahin",
    "age": 22,
    "city": "Dhaka"

  },
  {
    "name": "Mim",
    "age": 20,
    "city": "Dhaka"

  },
  {
    "name": "Samiul",
    "age": 25,
    "city": "Dhaka"

  },
  {
    "name": "Rafi",
    "age": 23,
    "city": "Dhaka"

  },
  {
    "name": "Jahin",
    "age": 22,
    "city": "Dhaka"

  },
  {
    "name": "Mim",
    "age": 20,
    "city": "Dhaka"

  }


]